cipher21/__init__.py
cipher21/application.py
cipher21/arguments_parser.py
cipher21/blocking_io.py
cipher21/bytes_utils.py
cipher21/constants.py
cipher21/decrypter.py
cipher21/encrypter.py
cipher21/key.py
cipher21/null_stream.py
cipher21/operation_mode.py
cipher21/stream_attributes.py
cipher21/typing.py
cipher21-0.1.0b1.dist-info/LICENSE.txt
cipher21-0.1.0b1.dist-info/METADATA
cipher21-0.1.0b1.dist-info/WHEEL
cipher21-0.1.0b1.dist-info/entry_points.txt
cipher21-0.1.0b1.dist-info/top_level.txt
cipher21-0.1.0b1.dist-info/zip-safe
cipher21-0.1.0b1.dist-info/RECORD
