Metadata-Version: 2.1
Name: cipher21
Version: 0.1.0b1
Summary: Stream modern cipher simple application for 2021 year which uses XChaCha20-Poly1305
Home-page: https://github.com/ksurdacki/cipher21
Author: Krzysztof Piotr Surdacki
License: The MIT License
Keywords: cli, console, command line, cipher, stream cipher, modern cipher,,encrypt, encryption, encrypter, ChaCha, XChaCha, ChaCha20, XChaCha20, Poly1305,,Authenticated Encryption, AE, AEAD, AES, AES256, 256 bit key
Platform: UNKNOWN
Classifier: License :: OSI Approved :: MIT License
Classifier: Operating System :: OS Independent
Classifier: Development Status :: 4 - Beta
Classifier: Environment :: Console
Classifier: Intended Audience :: End Users/Desktop
Classifier: Intended Audience :: Developers
Classifier: Intended Audience :: Information Technology
Classifier: Intended Audience :: System Administrators
Classifier: Intended Audience :: Telecommunications Industry
Classifier: Natural Language :: English
Classifier: Programming Language :: Python :: 3 :: Only
Classifier: Programming Language :: Python :: 3.6
Classifier: Programming Language :: Python :: 3.7
Classifier: Programming Language :: Python :: 3.8
Classifier: Programming Language :: Python :: 3.9
Classifier: Topic :: Security :: Cryptography
Requires-Python: ~=3.6
Requires-Dist: pycryptodome (~=3.10.1)
